rTools/__init__.py
rTools/config.py
rTools/main.py
rTools/json_yaml/__init__.py
rTools/json_yaml/json_yaml_convert.py
rTinyTools-0.0.3.dist-info/METADATA
rTinyTools-0.0.3.dist-info/WHEEL
rTinyTools-0.0.3.dist-info/entry_points.txt
rTinyTools-0.0.3.dist-info/top_level.txt
rTinyTools-0.0.3.dist-info/RECORD
